{
  "id": "social-feed-storytelling-interactive-1764387269525",
  "category": "social-feed",
  "theme": "Storytelling Interactive",
  "variant": "1764387269525",
  "description": "Storytelling Interactive themed social-feed",
  "keywords": [
    "social",
    "feed",
    "want",
    "build",
    "board",
    "game",
    "chat",
    "hero",
    "form",
    "card-layout"
  ],
  "placeholders": {
    "HERO_TITLE": "Main headline that captures the app's purpose (max 60 chars)",
    "FEATURE_TITLE": "Feature section heading (max 40 chars)",
    "FEATURE_1_TITLE": "Feature section heading 1 (max 40 chars)",
    "FEATURE_2_TITLE": "Feature section heading 2 (max 40 chars)",
    "FEATURE_3_TITLE": "Feature section heading 3 (max 40 chars)",
    "FEATURE_4_TITLE": "Feature section heading 4 (max 40 chars)",
    "FEATURE_5_TITLE": "Feature section heading 5 (max 40 chars)",
    "FEATURE_6_TITLE": "Feature section heading 6 (max 40 chars)",
    "FEATURE_7_TITLE": "Feature section heading 7 (max 40 chars)",
    "CTA_PRIMARY": "Action button text (max 30 chars)",
    "CTA_SECONDARY": "Secondary action button text (max 30 chars)",
    "CTA_1": "Action button 1 text (max 30 chars)",
    "CTA_2": "Action button 2 text (max 30 chars)",
    "DESCRIPTION": "Descriptive text that explains features or benefits",
    "DESCRIPTION_1": "Descriptive text 1 that explains features or benefits",
    "DESCRIPTION_2": "Descriptive text 2 that explains features or benefits",
    "DESCRIPTION_3": "Descriptive text 3 that explains features or benefits",
    "DESCRIPTION_4": "Descriptive text 4 that explains features or benefits",
    "DESCRIPTION_5": "Descriptive text 5 that explains features or benefits",
    "DESCRIPTION_6": "Descriptive text 6 that explains features or benefits",
    "DESCRIPTION_7": "Descriptive text 7 that explains features or benefits"
  },
  "code": "const BoardGameChatHero = () => {\n  return (\n    <div className=\"min-h-screen bg-gradient-to-b from-amber-50 via-orange-50 to-red-50\">\n      {/* Hero Section with Narrative Introduction */}\n      <div className=\"relative overflow-hidden\">\n        <div className=\"max-w-7xl mx-auto px-4 py-16\">\n          <div className=\"text-center mb-12\">\n            <h1 className=\"text-6xl font-bold text-gray-900 mb-6 leading-tight\">{{HERO_TITLE}}</h1>\n            <p className=\"text-xl text-gray-700 max-w-3xl mx-auto mb-8\">{{DESCRIPTION}}</p>\n          </div>\n\n          {/* Story Cards - Scroll-based narrative */}\n          <div className=\"space-y-24 mb-24\">\n            {/* Chapter 1 - Discovery */}\n            <div className=\"flex flex-col md:flex-row items-center gap-8\">\n              <div className=\"md:w-1/2 space-y-4\">\n                <div className=\"inline-block px-4 py-2 bg-orange-100 rounded-full text-orange-800 font-semibold text-sm mb-4\">\n                  Chapter 1: Discovery\n                </div>\n                <h2 className=\"text-4xl font-bold text-gray-900\">{{FEATURE_TITLE}}</h2>\n                <p className=\"text-lg text-gray-600 leading-relaxed\">{{DESCRIPTION_1}}</p>\n                <div className=\"flex gap-4 pt-4\">\n                  <button className=\"bg-orange-600 text-white px-6 py-3 rounded-lg font-semibold hover:bg-orange-700 transition-colors\">{{CTA_PRIMARY}}</button>\n                  <button className=\"border-2 border-orange-600 text-orange-600 px-6 py-3 rounded-lg font-semibold hover:bg-orange-50 transition-colors\">{{CTA_SECONDARY}}</button>\n                </div>\n              </div>\n              <div className=\"md:w-1/2\">\n                <img \n                  src=\"https://picsum.photos/id/244/800/600\" \n                  alt=\"Board game community gathering\"\n                  className=\"rounded-2xl shadow-2xl w-full h-96 object-cover\"\n                />\n              </div>\n            </div>\n\n            {/* Chapter 2 - Connection */}\n            <div className=\"flex flex-col md:flex-row-reverse items-center gap-8\">\n              <div className=\"md:w-1/2 space-y-4\">\n                <div className=\"inline-block px-4 py-2 bg-red-100 rounded-full text-red-800 font-semibold text-sm mb-4\">\n                  Chapter 2: Connection\n                </div>\n                <h2 className=\"text-4xl font-bold text-gray-900\">{{FEATURE_1_TITLE}}</h2>\n                <p className=\"text-lg text-gray-600 leading-relaxed\">{{DESCRIPTION_2}}</p>\n                <div className=\"bg-white rounded-xl p-6 shadow-lg space-y-3\">\n                  <div className=\"flex items-start gap-3\">\n                    <div className=\"w-10 h-10 rounded-full bg-gradient-to-br from-orange-400 to-red-400 flex items-center justify-center text-white font-bold\">\n                      M\n                    </div>\n                    <div className=\"flex-1\">\n                      <div className=\"font-semibold text-gray-900\">Marcus</div>\n                      <div className=\"text-gray-600 text-sm\">Hey! Anyone up for Gloomhaven this Saturday?</div>\n                    </div>\n                  </div>\n                  <div className=\"flex items-start gap-3\">\n                    <div className=\"w-10 h-10 rounded-full bg-gradient-to-br from-blue-400 to-purple-400 flex items-center justify-center text-white font-bold\">\n                      J\n                    </div>\n                    <div className=\"flex-1\">\n                      <div className=\"font-semibold text-gray-900\">Jessica</div>\n                      <div className=\"text-gray-600 text-sm\">Count me in! The usual spot at 2pm?</div>\n                    </div>\n                  </div>\n                </div>\n              </div>\n              <div className=\"md:w-1/2\">\n                <img \n                  src=\"https://picsum.photos/id/274/800/600\" \n                  alt=\"Friends playing board games\"\n                  className=\"rounded-2xl shadow-2xl w-full h-96 object-cover\"\n                />\n              </div>\n            </div>\n\n            {/* Chapter 3 - Community */}\n            <div className=\"flex flex-col md:flex-row items-center gap-8\">\n              <div className=\"md:w-1/2 space-y-4\">\n                <div className=\"inline-block px-4 py-2 bg-amber-100 rounded-full text-amber-800 font-semibold text-sm mb-4\">\n                  Chapter 3: Community\n                </div>\n                <h2 className=\"text-4xl font-bold text-gray-900\">{{FEATURE_2_TITLE}}</h2>\n                <p className=\"text-lg text-gray-600 leading-relaxed\">{{DESCRIPTION_3}}</p>\n                <div className=\"grid grid-cols-3 gap-4 pt-4\">\n                  <div className=\"bg-white rounded-lg p-4 text-center shadow-md\">\n                    <div className=\"text-3xl font-bold text-orange-600\">2,847</div>\n                    <div className=\"text-sm text-gray-600\">Active Players</div>\n                  </div>\n                  <div className=\"bg-white rounded-lg p-4 text-center shadow-md\">\n                    <div className=\"text-3xl font-bold text-red-600\">156</div>\n                    <div className=\"text-sm text-gray-600\">Local Groups</div>\n                  </div>\n                  <div className=\"bg-white rounded-lg p-4 text-center shadow-md\">\n                    <div className=\"text-3xl font-bold text-amber-600\">1,200+</div>\n                    <div className=\"text-sm text-gray-600\">Games Played</div>\n                  </div>\n                </div>\n              </div>\n              <div className=\"md:w-1/2\">\n                <img \n                  src=\"https://picsum.photos/id/367/800/600\" \n                  alt=\"Board game tournament\"\n                  className=\"rounded-2xl shadow-2xl w-full h-96 object-cover\"\n                />\n              </div>\n            </div>\n          </div>\n\n          {/* Call to Action - Final Chapter */}\n          <div className=\"relative\">\n            <div className=\"bg-gradient-to-r from-orange-600 to-red-600 rounded-3xl p-12 text-center text-white shadow-2xl\">\n              <div className=\"inline-block px-4 py-2 bg-white/20 rounded-full text-white font-semibold text-sm mb-6\">\n                Your Story Begins Now\n              </div>\n              <h2 className=\"text-5xl font-bold mb-6\">{{FEATURE_3_TITLE}}</h2>\n              <p className=\"text-xl mb-8 max-w-2xl mx-auto opacity-90\">{{DESCRIPTION_4}}</p>\n              <div className=\"flex flex-col sm:flex-row gap-4 justify-center items-center\">\n                <button className=\"bg-white text-orange-600 px-8 py-4 rounded-lg font-bold text-lg hover:bg-gray-100 transition-colors shadow-lg\">{{CTA_1}}</button>\n                <button className=\"border-2 border-white text-white px-8 py-4 rounded-lg font-bold text-lg hover:bg-white/10 transition-colors\">{{CTA_2}}</button>\n              </div>\n              <div className=\"mt-8 text-sm opacity-75\">\n                Free to join • No credit card required • Connect instantly\n              </div>\n            </div>\n          </div>\n\n          {/* Featured Stories */}\n          <div className=\"mt-24\">\n            <h3 className=\"text-3xl font-bold text-gray-900 text-center mb-12\">{{FEATURE_4_TITLE}}</h3>\n            <div className=\"grid md:grid-cols-3 gap-8\">\n              <div className=\"bg-white rounded-xl overflow-hidden shadow-lg hover:shadow-2xl transition-shadow\">\n                <img \n                  src=\"https://picsum.photos/id/0/800/600\" \n                  alt=\"Board game meetup\"\n                  className=\"w-full h-48 object-cover\"\n                />\n                <div className=\"p-6\">\n                  <h4 className=\"text-xl font-bold text-gray-900 mb-3\">{{FEATURE_5_TITLE}}</h4>\n                  <p className=\"text-gray-600 mb-4\">{{DESCRIPTION_5}}</p>\n                  <div className=\"text-orange-600 font-semibold\">— Emily, Seattle</div>\n                </div>\n              </div>\n              <div className=\"bg-white rounded-xl overflow-hidden shadow-lg hover:shadow-2xl transition-shadow\">\n                <img \n                  src=\"https://picsum.photos/id/180/800/600\" \n                  alt=\"Friends enjoying games\"\n                  className=\"w-full h-48 object-cover\"\n                />\n                <div className=\"p-6\">\n                  <h4 className=\"text-xl font-bold text-gray-900 mb-3\">{{FEATURE_6_TITLE}}</h4>\n                  <p className=\"text-gray-600 mb-4\">{{DESCRIPTION_6}}</p>\n                  <div className=\"text-orange-600 font-semibold\">— David, Austin</div>\n                </div>\n              </div>\n              <div className=\"bg-white rounded-xl overflow-hidden shadow-lg hover:shadow-2xl transition-shadow\">\n                <img \n                  src=\"https://picsum.photos/id/244/800/600\" \n                  alt=\"Game night celebration\"\n                  className=\"w-full h-48 object-cover\"\n                />\n                <div className=\"p-6\">\n                  <h4 className=\"text-xl font-bold text-gray-900 mb-3\">{{FEATURE_7_TITLE}}</h4>\n                  <p className=\"text-gray-600 mb-4\">{{DESCRIPTION_7}}</p>\n                  <div className=\"text-orange-600 font-semibold\">— Rachel, Denver</div>\n                </div>\n              </div>\n            </div>\n          </div>\n        </div>\n      </div>\n    </div>\n  );\n};",
  "usageCount": 0,
  "createdAt": "2025-11-29T03:34:29.619Z",
  "updatedAt": "2025-11-29T03:34:29.619Z"
}